{
    "title": "可爱晕咯～周大福居然出了草莓🍓味的蛋糕！",
    "description": "布林布林带着细闪的草莓淋面蛋糕上还带着漂亮的小蝴蝶结🎀耶\n虽然不含糖！\n却甜到心坎上了！！！！\nsoinlove的设计师是吃可爱长大的叭💕💕\n#女生生日礼物 #足金 #黄金蛋糕",
    "date": "08-21 广东",
    "comments": [
        "好可爱",
        "可以五折吗",
        "想要🎂+🍩+🍦",
        "多少g",
        "上报六月寒",
        "3k多",
        "这个什么价格",
        "好可爱啊",
        "多少克",
        "那我可记在小本本上了",
        "@Abhorrent (开心版)",
        "@momo🥕 不贵，我有钱了送你",
        "这是一口价嘛",
        "怎么卖",
        "@珊君君君 好喜欢",
        "@痞老板 @柚柚 @🌍 @ᅠᅠᅠ @一拳干废你 @绝版痛 给我买",
        "@小小怪下士 等你赚钱了送我这个生日礼物",
        "我的集美子，整天看的好美丽，过两年买",
        "好可爱！看起来香香软软的"
    ],
    "image": [
        "1040g008316otr70k0q205oj4m2locs9r62m71no!nd_dft_wlteh_webp_3_0.jpg",
        "1040g008316otr70k0q005oj4m2locs9rbbiio40!nd_dft_wlteh_webp_3_1.jpg",
        "1040g008316otr70k0q0g5oj4m2locs9rrl8qrr8!nd_dft_wlteh_webp_3_2.jpg",
        "1040g008316otr70k0q105oj4m2locs9r6huecc8!nd_dft_wlteh_webp_3_3.jpg",
        "1040g008316otr70k0q1g5oj4m2locs9rq6ekrs8!nd_dft_wlteh_webp_3_4.jpg"
    ],
    "label": 1
}