{
    "title": "有没有只涂素颜霜+散粉的姐妹？？！！",
    "description": "姐妹们！！！感觉怎么样啊。最近老是刷到这个组合说是很顶，搞得我都心动了，看了很多的帖子，也有超多人说会搓泥和假白。。。平常也不咋用素颜霜，有没有比较好用的素颜霜呀姐妹们~我也想试试#素颜霜#平价素颜霜#伪素颜#不懂就问有问必答#求助#早八#素颜霜真的好用吗",
    "date": "08-10",
    "comments": [
        "➕1⃣️",
        "补水喷雾➕防晒➕隔离➕散粉",
        "heaven pink➕沛然",
        "千万别买卡姿兰明星素颜霜，假白，搓泥",
        "真的很顶",
        "其实也行因为我也没有买水乳便宜的不敢用贵的我笨手笨脚怕打碎买了我又懒得涂，可以化妆前一天睡前擦b5精华随便什么牌子帝二天就不会很卡粉，我妆前也会擦亲测好用",
        "哈哈哈我闻着味儿就来了，有没有用过hosono的蓝色的罐罐的姐妹，挺薄的妆感我喜欢",
        "宫芙素颜霜还可以，用光一只了",
        "穿校服盖住",
        "我是黄偏黑皮，在学校，脸和脖子涂素颜霜会白了一点，但手臂不涂就会有色差，但全部涂又太浪费了怎么办",
        "姐妹你挺舍得给腮红的哈哈哈哈哈哈",
        "大数据怎么知道我今天是这样涂的",
        "我直接就用散粉，我是油皮，搞点散粉就不油了",
        "可以这样用的吗",
        "我是润色隔离+散粉，方便快捷",
        "防晒素颜霜➕粉饼亲测自然妈生好皮！！",
        "有 ，我就是",
        "没有水乳 化妆步骤隔离遮瑕粉底液可以吗",
        "hosono的那个罐罐还不错啦，挺扒脸的，我天天涂，照镜子都美个半天",
        "好使不姐妹"
    ],
    "image": [
        "1040g2sg316am7ooviod05pfarhg19dpi2oqa9m0!nd_dft_wlteh_webp_3_0.jpg"
    ],
    "label": 1
}