{
    "title": "喜欢住酒店的核心原因是人心太冷漠",
    "description": "一直觉得我要是有钱，就想要一辈子每天都住在五星级酒店里，喜欢一下车就有人帮忙开车门拎箱子，喜欢酒店的空调温度和香薰味道，喜欢不同建筑风格的大堂和公区，喜欢上百米挑高让人心胸开阔的大堂，喜欢可以眺望整个城市的景色的落地窗，喜欢放下行李🧳后悠哉悠哉地去行政酒廊吃点心喝下午茶，欣赏美景发呆放空，喜欢在夏天住酒店的时候穿上自己新买的泳衣🩱去漂亮的泳池🏊游泳，喜欢回到房间打开蓝牙音箱，浴缸里撒上浴盐开始放水，然后在黄昏的时候一边欣赏夕阳🌇一边泡澡🛀一边听歌…..\n\n一个人住酒店像一场场短暂又乐此不疲过家家，任何人只要愿意支付费用，见到的全是笑脸，无时无刻24小时只要一个电话总有亲切的回应，好像总有人为你随时待命，借此弥补内心缺失未曾被好好照顾的小孩儿。高档酒店比起住宿的实用价值，更多的是心理和情绪上磁场能量加持的附加价值，是在捉襟见肘的生活里给自己建立起的一个心灵短暂栖息之处，实在是比心理医生更治愈人心的存在。尽管是花钱兑换来的，但是谁又在乎呢，只要体验感是真的不就好了吗。\n\n这次在杭州staycation入住的酒店是位于钱江新城CBD的钱江新城万豪酒店，紧邻钱塘江，漫步就可以到达江边，傍晚太阳落山的时候去江边散步很city。离杭州大剧院，来福士广场都很近，去西湖打车20分钟左右。无论是房间还是行政酒廊都是正对着一线钱塘江景，看得让人心旷神怡心胸开阔，非常适合staycation。酒店的行政酒廊餐品挺丰富的，下午茶小甜点很好吃，在行政酒廊的高空看钱塘江，视野更开阔，无边无际的美。酒店的泳池也很值得一提，依然是可以欣赏江景，挑高很高，非常开阔，超级漂亮。夜晚在房间就可以欣赏钱塘江夜景🌃，步行五分钟就是城市阳台，可以欣赏灯光秀。\n\n#生活#生活方式#裸辞#裸辞的生活#infp#治愈#解压#放松#旅行#杭州#酒店#酒店推荐#万豪#独居#独处#落地窗#江景酒店",
    "date": "编辑于 08-24 江苏",
    "comments": [
        "有钱住五星级酒店肯定超级爽，我本科学酒店管理，学了四年怎么专业的细致的惊喜的对客服务，上课就觉得一晚上得多少钱才能享受这样的精致服务",
        "是的 钱就是买人和人的距离感的。头等舱商务座和酒店都是这样",
        "公司搞了几次培训团建让住瑰丽和四季，我都是准时的去办入住不想错过窝酒店的一分一秒哈哈。以前小公司销售没见过啥大世面，多亏了来到外企后不定期有惊喜住五星级。这下个月还搞一次团建排队去喜来登。",
        "如果是经常能住高级酒店的人，自己的房子应该也不差的。如果你说的是那种大别墅庄园，还要有各种入流的艺术品，一般的有钱人也负担不起的",
        "我也喜欢 有钱就好了",
        "什么意思 展开说说",
        "嗯嗯比不上比不上",
        "同城住酒店是最轻松不累的！",
        "刚从朗廷离店，品味格调还是有区别的",
        "哈哈 说的对",
        "你得很有钱，当你没钱交房费的时候就知道有自己产权的一套房才是不流浪的保障。",
        "哪个酒店都不如自己的干干净净清清爽爽的小窝",
        "谁问你了别人晒一下出去下馆子你是不是也要说句外边做饭脏不像你家里用的都是好锅碗自己做才放心？",
        "说白了楼主是看重有人服务，而且被服务的感觉很好啊，不懂的人是没有被服务过吧",
        "觉得酒店脏，真的不爱，五星级酒店卫生不过关也是老生常谈了。我家里很舒服，毕竟是花了钱在软装的，灯光床垫沙发都是中上级别，够我用了。",
        "怎么总有人喜欢代入自己的生活水平操心别人啊",
        "羡慕带薪住好酒店的 这种班儿我也愿意上",
        "头等舱和商务座真的省心很多 隔绝嘈杂的世界和物种的多样性",
        "可是我咋感觉真正的豪宅会比酒店奢华很多呢因为可以按照自己的理念去设计 并且购置奢华的艺术品🖼️",
        "同喜欢住酒店的人 尤其同城 真的放松 不过大多数人都不爱 哈哈"
    ],
    "image": [
        "1040g2sg316q2024ejk005on7e4gnqt7sppg1tqg!nd_dft_wlteh_webp_3_0.jpg",
        "1040g2sg316q2022sgmd05on7e4gnqt7s4kvvo9o!nd_dft_wlteh_webp_3_2.jpg",
        "1040g2sg316q2022sgmdg5on7e4gnqt7s8b4ptrg!nd_dft_wlteh_webp_3_3.jpg",
        "1040g2sg316q2022sgm705on7e4gnqt7s2c7pfno!nd_dft_wlteh_webp_3_4.jpg",
        "1040g2sg316q2022sgm7g5on7e4gnqt7s4gp4qj0!nd_dft_wlteh_webp_3_5.jpg",
        "1040g2sg316q2022sgm805on7e4gnqt7sbiutrr8!nd_dft_wlteh_webp_3_6.jpg",
        "1040g2sg316q2022sgm8g5on7e4gnqt7sqvg03go!nd_dft_wlteh_webp_3_7.jpg",
        "1040g2sg316q2022sgm905on7e4gnqt7sajqvs10!nd_dft_wlteh_webp_3_8.jpg",
        "1040g2sg316q2022sgm9g5on7e4gnqt7skckq580!nd_dft_wlteh_webp_3_9.jpg",
        "1040g2sg316q2022sgma05on7e4gnqt7snout158!nd_dft_wlteh_webp_3_10.jpg",
        "1040g2sg316q2022sgmb05on7e4gnqt7srj6u880!nd_dft_wlteh_webp_3_11.jpg",
        "1040g2sg316q2022sgmag5on7e4gnqt7s302uot8!nd_dft_wlteh_webp_3_12.jpg",
        "1040g2sg316q2022sgmbg5on7e4gnqt7so6jt070!nd_dft_wlteh_webp_3_13.jpg",
        "1040g2sg316q2022sgmc05on7e4gnqt7s007n1q8!nd_dft_wlteh_webp_3_14.jpg",
        "1040g2sg316q2022sgmcg5on7e4gnqt7s6bhj6qo!nd_dft_wlteh_webp_3_15.jpg",
        "1040g2sg316q2024ejk0g5on7e4gnqt7sto2nbqo!nd_dft_wlteh_webp_3_16.jpg",
        "1040g2sg316q2024ejk105on7e4gnqt7sf3eaju0!nd_dft_wlteh_webp_3_17.jpg"
    ],
    "label": 0
}